{
  "component-definition": {
    "uuid": "c3aaa533-a73b-4c07-8a92-d72984fece05",
    "metadata": {
      "title": "APP.4.8 Benutzerdefiniert: Graphdatenbanken",
      "last-modified": "2025-11-14T19:05:33.016905+00:00",
      "version": "1.0.0",
      "oscal-version": "1.1.3"
    },
    "components": [
      {
        "uuid": "74ba19d1-cbac-4d88-95e6-91672d8893e1",
        "type": "software",
        "title": "APP.4.8 Benutzerdefiniert: Graphdatenbanken",
        "description": "This component imports the profile for Baustein APP.4.8.",
        "control-implementations": [
          {
            "uuid": "d2cb996d-6a31-4879-bd7c-c2f197217fe2",
            "source": "https://raw.githubusercontent.com/AG-3-Nutzergenerierte-Inhalte/Stand-der-Technik-Bibliothek/refs/heads/main/Stand-der-Technik-Bibliothek/Kompendien/Grundschutz++-Kompendium/profile/anwendungen_profile.json",
            "description": "Imports all controls from the profile for Baustein APP.4.8.",
            "implemented-requirements": [
              {
                "uuid": "4e804ddc-32d0-4b58-b281-9a055c15e45e",
                "control-id": "ARCH.7.1",
                "description": "This control is implemented as defined in the profile."
              },
              {
                "uuid": "45b77120-38ab-4f1b-9a71-6ea49cdfb827",
                "control-id": "ARCH.8.3",
                "description": "This control is implemented as defined in the profile."
              },
              {
                "uuid": "5aa82dab-3d7d-40df-ac29-716658a8f1fa",
                "control-id": "ARCH.9.2",
                "description": "This control is implemented as defined in the profile."
              },
              {
                "uuid": "a36e9920-6f2a-4a39-bbbd-e3d95391f13f",
                "control-id": "ARCH.9.3",
                "description": "This control is implemented as defined in the profile."
              },
              {
                "uuid": "7af44e42-64e1-4df2-b148-91d274858c71",
                "control-id": "ARCH.9.4",
                "description": "This control is implemented as defined in the profile."
              },
              {
                "uuid": "0b53bc3b-9a5f-4e71-853e-f224d200987f",
                "control-id": "ASST.2.3.2",
                "description": "This control is implemented as defined in the profile."
              },
              {
                "uuid": "ef9f26d9-1ec6-4dee-af9c-2b12445f2871",
                "control-id": "ASST.7.1",
                "description": "This control is implemented as defined in the profile."
              },
              {
                "uuid": "4f13a72f-11c8-484c-a2c3-adc1300ca9a4",
                "control-id": "BER.3.11",
                "description": "This control is implemented as defined in the profile."
              },
              {
                "uuid": "7aaf064b-18be-4e36-875c-e1ef67280fdb",
                "control-id": "BER.3.6",
                "description": "This control is implemented as defined in the profile."
              },
              {
                "uuid": "5f0d072b-e59f-4bf8-877a-ce2dba2bcfe9",
                "control-id": "BER.3.9",
                "description": "This control is implemented as defined in the profile."
              },
              {
                "uuid": "a50441c0-d3a8-464c-b73f-30087f98592a",
                "control-id": "BER.4.6",
                "description": "This control is implemented as defined in the profile."
              },
              {
                "uuid": "a88343fa-0a85-46d0-8f0d-1e9d5d14f7d5",
                "control-id": "BER.6.4",
                "description": "This control is implemented as defined in the profile."
              },
              {
                "uuid": "8a0acd50-553a-47c3-912c-b80db2936c91",
                "control-id": "BES.2.1.3",
                "description": "This control is implemented as defined in the profile."
              },
              {
                "uuid": "1cff41ff-f5d5-4076-847c-21f88858a0e4",
                "control-id": "BES.2.1.5",
                "description": "This control is implemented as defined in the profile."
              },
              {
                "uuid": "af8be63f-6161-4a13-ae48-47c8180d1b6b",
                "control-id": "DET.3.1.10",
                "description": "This control is implemented as defined in the profile."
              },
              {
                "uuid": "74da4a20-51b9-4b66-b725-9485d742aa7d",
                "control-id": "DET.3.1.11",
                "description": "This control is implemented as defined in the profile."
              },
              {
                "uuid": "40b544fb-bef5-4c3a-8015-6ff65940b1f1",
                "control-id": "DET.3.1.12",
                "description": "This control is implemented as defined in the profile."
              },
              {
                "uuid": "1dd78be1-072a-4656-a145-6c171f79ca3f",
                "control-id": "DET.3.1.4",
                "description": "This control is implemented as defined in the profile."
              },
              {
                "uuid": "0b0f8b12-f7d7-4e53-8398-ee77094563c6",
                "control-id": "DET.4.13",
                "description": "This control is implemented as defined in the profile."
              },
              {
                "uuid": "00d0e44b-8bd2-4efa-b70b-ea881bebb540",
                "control-id": "DET.4.15",
                "description": "This control is implemented as defined in the profile."
              },
              {
                "uuid": "6ded735e-cc48-4968-a767-aed0b597f26e",
                "control-id": "DET.4.16",
                "description": "This control is implemented as defined in the profile."
              },
              {
                "uuid": "03997756-c719-401b-a0da-6cea0f41cab7",
                "control-id": "DET.4.5",
                "description": "This control is implemented as defined in the profile."
              },
              {
                "uuid": "9e6e7222-69d6-4024-b456-79fa5cb3bebc",
                "control-id": "DET.5.10.5",
                "description": "This control is implemented as defined in the profile."
              },
              {
                "uuid": "4fd49e31-ea8a-4114-af8c-384c9000d156",
                "control-id": "DEV.2.2",
                "description": "This control is implemented as defined in the profile."
              },
              {
                "uuid": "12155c26-0330-4594-8bb3-52f9d94aa9f9",
                "control-id": "DEV.2.3",
                "description": "This control is implemented as defined in the profile."
              },
              {
                "uuid": "a0795a00-9120-4298-bdc1-04c0d83d9619",
                "control-id": "DEV.2.5",
                "description": "This control is implemented as defined in the profile."
              },
              {
                "uuid": "f8b475e5-f6ab-402a-8dd6-13e663f8bb3d",
                "control-id": "DEV.2.6",
                "description": "This control is implemented as defined in the profile."
              },
              {
                "uuid": "32c6e8fa-571b-420e-b2e0-8d89d14d599e",
                "control-id": "DEV.2.6.1",
                "description": "This control is implemented as defined in the profile."
              },
              {
                "uuid": "63700b29-b863-4ac6-91a2-da8bbb249e32",
                "control-id": "DEV.2.6.2",
                "description": "This control is implemented as defined in the profile."
              },
              {
                "uuid": "e604979a-dfab-43fe-95ba-91cb31e7c334",
                "control-id": "DEV.3.1",
                "description": "This control is implemented as defined in the profile."
              },
              {
                "uuid": "f808bc17-5c0a-4478-a9c4-5f3d36f0d4d0",
                "control-id": "DEV.3.2",
                "description": "This control is implemented as defined in the profile."
              },
              {
                "uuid": "b134e1a1-0b74-4d9d-a136-22cea6e0a4fa",
                "control-id": "DEV.3.3",
                "description": "This control is implemented as defined in the profile."
              },
              {
                "uuid": "4bf953fd-c51a-4773-bd9d-429742b36282",
                "control-id": "DEV.3.4",
                "description": "This control is implemented as defined in the profile."
              },
              {
                "uuid": "172415c5-cbe0-4c34-9563-96626a29b125",
                "control-id": "DEV.4.1",
                "description": "This control is implemented as defined in the profile."
              },
              {
                "uuid": "184bce4c-de74-4b59-a489-7ad8473b2916",
                "control-id": "DEV.4.10",
                "description": "This control is implemented as defined in the profile."
              },
              {
                "uuid": "4cc72e88-5c05-49be-9307-371aec518532",
                "control-id": "DEV.4.11",
                "description": "This control is implemented as defined in the profile."
              },
              {
                "uuid": "9e1d51dc-5435-45af-b2bf-e12d0a5c3f48",
                "control-id": "DEV.4.2",
                "description": "This control is implemented as defined in the profile."
              },
              {
                "uuid": "9badd105-a12e-436d-89ba-ffc5e471ad39",
                "control-id": "DEV.4.3",
                "description": "This control is implemented as defined in the profile."
              },
              {
                "uuid": "f91051a1-2faf-4098-bb7a-fac9cfcb93de",
                "control-id": "DEV.4.4",
                "description": "This control is implemented as defined in the profile."
              },
              {
                "uuid": "6ad54c3d-1f0b-496f-b098-f38ff9f528f4",
                "control-id": "DEV.4.5",
                "description": "This control is implemented as defined in the profile."
              },
              {
                "uuid": "5df4215b-3702-4046-bc23-26a288fe8d1e",
                "control-id": "DEV.4.6",
                "description": "This control is implemented as defined in the profile."
              },
              {
                "uuid": "0fecfe45-b89f-48a5-a2cd-03c2ffc36c2d",
                "control-id": "DEV.4.7",
                "description": "This control is implemented as defined in the profile."
              },
              {
                "uuid": "bccade1d-3063-4878-ab63-999ff53992f3",
                "control-id": "DEV.4.8",
                "description": "This control is implemented as defined in the profile."
              },
              {
                "uuid": "092d219e-59cd-4ace-813d-442e6b60e574",
                "control-id": "DEV.4.9",
                "description": "This control is implemented as defined in the profile."
              },
              {
                "uuid": "769c81c0-7b8b-4167-a6bf-e91254139872",
                "control-id": "DEV.5.1",
                "description": "This control is implemented as defined in the profile."
              },
              {
                "uuid": "6166de68-c739-45b8-a74f-a9c769f8b9db",
                "control-id": "DEV.5.2",
                "description": "This control is implemented as defined in the profile."
              },
              {
                "uuid": "11051852-3313-4ee6-bea2-d12bb443beba",
                "control-id": "DEV.5.3",
                "description": "This control is implemented as defined in the profile."
              },
              {
                "uuid": "ed1bf472-df01-4078-b5f1-2e7b0b1dc0aa",
                "control-id": "DEV.7.2",
                "description": "This control is implemented as defined in the profile."
              },
              {
                "uuid": "f1b9db60-5aa6-4e9b-aaad-bf03bf336434",
                "control-id": "KONF.10.1",
                "description": "This control is implemented as defined in the profile."
              },
              {
                "uuid": "770756ce-fb10-41aa-aea0-a83ebd374734",
                "control-id": "KONF.10.1.1",
                "description": "This control is implemented as defined in the profile."
              },
              {
                "uuid": "6bf40e20-2392-433d-a2e2-9b303f6a59a0",
                "control-id": "KONF.10.2",
                "description": "This control is implemented as defined in the profile."
              },
              {
                "uuid": "1b48e72f-cac8-45f8-bd1d-3ea6916ed0f2",
                "control-id": "KONF.10.3",
                "description": "This control is implemented as defined in the profile."
              },
              {
                "uuid": "79901da5-b431-4a87-91a2-db5a273cdc9f",
                "control-id": "KONF.10.4",
                "description": "This control is implemented as defined in the profile."
              },
              {
                "uuid": "e074cf6b-d031-4b53-a704-a6614f17e35f",
                "control-id": "KONF.10.5",
                "description": "This control is implemented as defined in the profile."
              },
              {
                "uuid": "3f1a5226-64e1-4dd8-aa01-e66667083df0",
                "control-id": "KONF.10.5.1",
                "description": "This control is implemented as defined in the profile."
              },
              {
                "uuid": "eb48c43b-d467-4c97-acd8-8c9dadb43e67",
                "control-id": "KONF.11.1",
                "description": "This control is implemented as defined in the profile."
              },
              {
                "uuid": "2c6ffb8f-68b3-4e79-a69c-d994d6cba5fa",
                "control-id": "KONF.11.1.2",
                "description": "This control is implemented as defined in the profile."
              },
              {
                "uuid": "7e7b39ed-e8b2-4aae-b2ee-73c7516b3122",
                "control-id": "KONF.11.3",
                "description": "This control is implemented as defined in the profile."
              },
              {
                "uuid": "0679878f-8c3f-41f6-be12-4b887fa15c39",
                "control-id": "KONF.11.7",
                "description": "This control is implemented as defined in the profile."
              },
              {
                "uuid": "cbd9c948-033c-48aa-a269-44f83494d759",
                "control-id": "KONF.11.8",
                "description": "This control is implemented as defined in the profile."
              },
              {
                "uuid": "da8703c8-dd23-4c49-aef7-732b33bc7132",
                "control-id": "KONF.11.9",
                "description": "This control is implemented as defined in the profile."
              },
              {
                "uuid": "22bec01f-11d2-43c4-b661-4e8f632039e5",
                "control-id": "KONF.12.1",
                "description": "This control is implemented as defined in the profile."
              },
              {
                "uuid": "0d355fbb-67b3-4e62-8d9c-de0053914bb5",
                "control-id": "KONF.14.1",
                "description": "This control is implemented as defined in the profile."
              },
              {
                "uuid": "601e2e5d-5a01-405b-8c4f-1c9b055f2331",
                "control-id": "KONF.14.1.1",
                "description": "This control is implemented as defined in the profile."
              },
              {
                "uuid": "9629199d-63b3-4e75-af07-d6e3b44781d0",
                "control-id": "KONF.14.1.2",
                "description": "This control is implemented as defined in the profile."
              },
              {
                "uuid": "8dc9df01-eb73-4e9c-bb73-9fbc70693509",
                "control-id": "KONF.14.5",
                "description": "This control is implemented as defined in the profile."
              },
              {
                "uuid": "29e46369-9e5c-41a6-915f-bb53c9f18c0a",
                "control-id": "KONF.6.13",
                "description": "This control is implemented as defined in the profile."
              },
              {
                "uuid": "1d1ab81b-c8e9-498a-9972-26bc596f2d82",
                "control-id": "KONF.6.6",
                "description": "This control is implemented as defined in the profile."
              },
              {
                "uuid": "282748f3-85d7-4ea3-a072-4035dbe8f096",
                "control-id": "KONF.6.6.1",
                "description": "This control is implemented as defined in the profile."
              },
              {
                "uuid": "3bcf9684-4965-42a7-9f73-7737557dec2f",
                "control-id": "KONF.6.7",
                "description": "This control is implemented as defined in the profile."
              },
              {
                "uuid": "0634a425-63a4-4a9f-bec8-3c5881b0861f",
                "control-id": "KONF.8.2",
                "description": "This control is implemented as defined in the profile."
              },
              {
                "uuid": "eeed4efe-caae-4563-b3d1-7c2d6b786b35",
                "control-id": "NOT.4.17",
                "description": "This control is implemented as defined in the profile."
              },
              {
                "uuid": "e256ee20-0d23-4ed6-8173-da0ac2dfe1d3",
                "control-id": "NOT.4.3",
                "description": "This control is implemented as defined in the profile."
              }
            ]
          }
        ]
      }
    ]
  }
}