{
  "component-definition": {
    "uuid": "b9894d62-ba16-4770-a3c1-584efaccf888",
    "metadata": {
      "title": "IND.1 Prozessleit- und Automatisierungstechnik",
      "last-modified": "2025-11-14T19:05:36.787300+00:00",
      "version": "1.0.0",
      "oscal-version": "1.1.3"
    },
    "components": [
      {
        "uuid": "39f42d04-97de-4f4e-bdbc-3c7d59b8491b",
        "type": "software",
        "title": "IND.1 Prozessleit- und Automatisierungstechnik",
        "description": "This component imports the profile for Baustein IND.1.",
        "control-implementations": [
          {
            "uuid": "3a12e0db-527c-4019-82b3-2b7f176a5e67",
            "source": "https://raw.githubusercontent.com/AG-3-Nutzergenerierte-Inhalte/Stand-der-Technik-Bibliothek/refs/heads/main/Stand-der-Technik-Bibliothek/Kompendien/Grundschutz++-Kompendium/profile/ot-systeme_profile.json",
            "description": "Imports all controls from the profile for Baustein IND.1.",
            "implemented-requirements": [
              {
                "uuid": "758c9b63-0dff-4a85-be89-fc659f7ee247",
                "control-id": "ARCH.2.2.11",
                "description": "This control is implemented as defined in the profile."
              },
              {
                "uuid": "d43c06dc-3f80-44df-bbcb-bcdbda0682bd",
                "control-id": "ARCH.2.2.5",
                "description": "This control is implemented as defined in the profile."
              },
              {
                "uuid": "ef4b4a26-1c7e-49d7-80e7-09cfb2236f28",
                "control-id": "ARCH.2.2.9",
                "description": "This control is implemented as defined in the profile."
              },
              {
                "uuid": "5a9d5a65-d874-4bc4-b068-0c5f75c57982",
                "control-id": "ARCH.5.3",
                "description": "This control is implemented as defined in the profile."
              },
              {
                "uuid": "72343f23-b760-4681-92bc-6afca74ef40f",
                "control-id": "ASST.2.3.1",
                "description": "This control is implemented as defined in the profile."
              },
              {
                "uuid": "062f6591-aac3-42c9-878e-37c3e1d824ef",
                "control-id": "ASST.3.3",
                "description": "This control is implemented as defined in the profile."
              },
              {
                "uuid": "5d498497-745e-43c7-86fa-83e78e503a5b",
                "control-id": "ASST.5.1",
                "description": "This control is implemented as defined in the profile."
              },
              {
                "uuid": "ac2e5324-6da6-4c0e-a126-dd293d28b1cc",
                "control-id": "ASST.5.2",
                "description": "This control is implemented as defined in the profile."
              },
              {
                "uuid": "242e05aa-b16d-4466-bdc1-73365e9e6bbc",
                "control-id": "ASST.5.3",
                "description": "This control is implemented as defined in the profile."
              },
              {
                "uuid": "f433489b-32a0-49cd-986d-5ed89e8ea614",
                "control-id": "ASST.5.4",
                "description": "This control is implemented as defined in the profile."
              },
              {
                "uuid": "dde75eec-aeec-41eb-bb85-3fbaa6f1e40d",
                "control-id": "ASST.5.5",
                "description": "This control is implemented as defined in the profile."
              },
              {
                "uuid": "0b8b15ad-6aab-485e-94d7-70668455bb31",
                "control-id": "ASST.5.7",
                "description": "This control is implemented as defined in the profile."
              },
              {
                "uuid": "2cf543b0-e8d5-4c36-b737-aea8abf3b26d",
                "control-id": "ASST.6.3",
                "description": "This control is implemented as defined in the profile."
              },
              {
                "uuid": "c60643e8-1e33-406f-9167-ce76583a3f36",
                "control-id": "ASST.6.4",
                "description": "This control is implemented as defined in the profile."
              },
              {
                "uuid": "0348db7f-129c-42bf-b314-07adac99456d",
                "control-id": "BER.3.10",
                "description": "This control is implemented as defined in the profile."
              },
              {
                "uuid": "47260c99-c568-465f-bb38-0da17add5d43",
                "control-id": "BER.3.17",
                "description": "This control is implemented as defined in the profile."
              },
              {
                "uuid": "b142ea02-f197-49ef-afa1-49767069027f",
                "control-id": "BER.3.8",
                "description": "This control is implemented as defined in the profile."
              },
              {
                "uuid": "e8fff1fa-2311-4de0-9e05-8e7b01f0083e",
                "control-id": "BER.4.5",
                "description": "This control is implemented as defined in the profile."
              },
              {
                "uuid": "d992bd5d-da5b-4105-8f76-7346c963c3a4",
                "control-id": "BER.4.7",
                "description": "This control is implemented as defined in the profile."
              },
              {
                "uuid": "cd70d680-06c7-4e60-93a1-c86d544a9197",
                "control-id": "DET.3.1.3",
                "description": "This control is implemented as defined in the profile."
              },
              {
                "uuid": "1edee8b4-7f3f-42de-9fbc-5414c52de001",
                "control-id": "DET.3.1.5",
                "description": "This control is implemented as defined in the profile."
              },
              {
                "uuid": "c290281f-7405-4307-b686-e4fa85365191",
                "control-id": "DET.3.1.6",
                "description": "This control is implemented as defined in the profile."
              },
              {
                "uuid": "e100a496-be74-4623-a858-1a4c5bf8f229",
                "control-id": "DET.3.1.7",
                "description": "This control is implemented as defined in the profile."
              },
              {
                "uuid": "2e16ce8e-d1d4-47ac-bd41-b5494283a700",
                "control-id": "DET.3.1.8",
                "description": "This control is implemented as defined in the profile."
              },
              {
                "uuid": "ff3c0d3c-bcb6-434d-a558-27fd81eaf9c5",
                "control-id": "DET.3.1.9",
                "description": "This control is implemented as defined in the profile."
              },
              {
                "uuid": "6dd1e391-3369-4177-a902-6e6fd2464b2c",
                "control-id": "DET.4.2",
                "description": "This control is implemented as defined in the profile."
              },
              {
                "uuid": "22545366-d104-463f-b927-416089cf0636",
                "control-id": "DET.4.8",
                "description": "This control is implemented as defined in the profile."
              },
              {
                "uuid": "6067a1d4-6a5b-4052-b749-48750b765249",
                "control-id": "DET.4.9",
                "description": "This control is implemented as defined in the profile."
              },
              {
                "uuid": "bb3f59e4-22db-4b62-8b9c-98fdf68c313f",
                "control-id": "DET.5.10.3",
                "description": "This control is implemented as defined in the profile."
              },
              {
                "uuid": "e759d63e-2f29-4b82-a303-eb69e83f5904",
                "control-id": "DET.5.10.4",
                "description": "This control is implemented as defined in the profile."
              },
              {
                "uuid": "0b4e48b7-8d00-42ac-adc9-64fcabe16067",
                "control-id": "GEB.6.4",
                "description": "This control is implemented as defined in the profile."
              },
              {
                "uuid": "9144c8ab-c37b-4d2f-96b1-bae88681cd4f",
                "control-id": "GEB.6.5",
                "description": "This control is implemented as defined in the profile."
              },
              {
                "uuid": "b2264348-166c-404c-9142-4779fd7bfa0e",
                "control-id": "GEB.7.1",
                "description": "This control is implemented as defined in the profile."
              },
              {
                "uuid": "608d8cd5-11fd-4109-b174-3048653bf648",
                "control-id": "GEB.7.2",
                "description": "This control is implemented as defined in the profile."
              },
              {
                "uuid": "415423c7-250a-4399-bbdf-68d5b0aaf047",
                "control-id": "KONF.2.1",
                "description": "This control is implemented as defined in the profile."
              },
              {
                "uuid": "4e7ebd32-c41a-469c-918f-ab30f9a6092c",
                "control-id": "KONF.2.1.1",
                "description": "This control is implemented as defined in the profile."
              },
              {
                "uuid": "3662f1df-caf0-4021-81d6-43a93d4ffd16",
                "control-id": "KONF.2.2",
                "description": "This control is implemented as defined in the profile."
              },
              {
                "uuid": "28e9e47b-2d41-4fd8-9377-41dbc61e1081",
                "control-id": "KONF.2.3",
                "description": "This control is implemented as defined in the profile."
              },
              {
                "uuid": "fda7febd-59e7-4dbc-a49b-bd6fd19ec545",
                "control-id": "KONF.2.4",
                "description": "This control is implemented as defined in the profile."
              },
              {
                "uuid": "d43f4f9b-305e-46f3-8e98-44a222bb5dba",
                "control-id": "KONF.2.4.1",
                "description": "This control is implemented as defined in the profile."
              },
              {
                "uuid": "29a238e2-f3c4-4573-9f2d-97a2880a78ed",
                "control-id": "KONF.2.4.2",
                "description": "This control is implemented as defined in the profile."
              },
              {
                "uuid": "092dbf4a-1719-40ff-953b-c91e0b8b7807",
                "control-id": "KONF.2.5",
                "description": "This control is implemented as defined in the profile."
              },
              {
                "uuid": "cba801c8-b61c-44b7-99f1-769d649473af",
                "control-id": "KONF.2.5.1",
                "description": "This control is implemented as defined in the profile."
              },
              {
                "uuid": "28c0ee4e-0d2a-40d0-a2f5-a939e7533b7a",
                "control-id": "KONF.2.6",
                "description": "This control is implemented as defined in the profile."
              },
              {
                "uuid": "fb4a53d9-fb84-432b-8c14-b766fc932957",
                "control-id": "KONF.2.7",
                "description": "This control is implemented as defined in the profile."
              },
              {
                "uuid": "2e17074c-55e5-4b8e-a305-835a27a93eff",
                "control-id": "KONF.2.8",
                "description": "This control is implemented as defined in the profile."
              },
              {
                "uuid": "e9f867a8-88bf-4855-825a-1b92d24bfd61",
                "control-id": "KONF.3.1",
                "description": "This control is implemented as defined in the profile."
              },
              {
                "uuid": "265b8c68-b85a-4615-92f4-191bd4b9deca",
                "control-id": "KONF.3.2",
                "description": "This control is implemented as defined in the profile."
              },
              {
                "uuid": "8ae1d5fd-6bb1-4753-afd0-56f636f754a3",
                "control-id": "KONF.3.3",
                "description": "This control is implemented as defined in the profile."
              },
              {
                "uuid": "0e5bf0f3-30ca-4988-af95-bb319dc0039e",
                "control-id": "KONF.3.5",
                "description": "This control is implemented as defined in the profile."
              },
              {
                "uuid": "10efd992-f66c-4221-a1a4-f7abeffe5d5f",
                "control-id": "KONF.3.7",
                "description": "This control is implemented as defined in the profile."
              },
              {
                "uuid": "bc6abc19-9089-4332-9477-7ccd34931cbb",
                "control-id": "KONF.3.8",
                "description": "This control is implemented as defined in the profile."
              },
              {
                "uuid": "cc079de9-ac83-4e1b-8e83-dee0a919844b",
                "control-id": "KONF.4.1",
                "description": "This control is implemented as defined in the profile."
              },
              {
                "uuid": "f92875a3-0317-4ad5-8f00-78f1a9f23b10",
                "control-id": "KONF.4.1.1",
                "description": "This control is implemented as defined in the profile."
              },
              {
                "uuid": "d49445e7-eef1-4899-9dad-9da7f465f54a",
                "control-id": "KONF.4.2",
                "description": "This control is implemented as defined in the profile."
              },
              {
                "uuid": "1f8a9236-36e9-4f4f-b710-f83c5b5fbd53",
                "control-id": "KONF.4.2.1",
                "description": "This control is implemented as defined in the profile."
              },
              {
                "uuid": "612eca28-efd7-4502-8300-a42f61c2b157",
                "control-id": "KONF.4.3",
                "description": "This control is implemented as defined in the profile."
              },
              {
                "uuid": "90974c60-457c-406d-8255-1a4fa8c26a63",
                "control-id": "KONF.4.4",
                "description": "This control is implemented as defined in the profile."
              },
              {
                "uuid": "6b481cde-d666-44da-bd45-feab4a4898d9",
                "control-id": "KONF.4.5",
                "description": "This control is implemented as defined in the profile."
              },
              {
                "uuid": "52a2d92e-e692-4637-941c-f95c27b9b664",
                "control-id": "KONF.5.1",
                "description": "This control is implemented as defined in the profile."
              },
              {
                "uuid": "c6081854-7cbc-4beb-9749-b586d3b2769a",
                "control-id": "KONF.5.1.1",
                "description": "This control is implemented as defined in the profile."
              },
              {
                "uuid": "aafd8eff-2822-4608-b862-b55b2a971af9",
                "control-id": "KONF.5.2",
                "description": "This control is implemented as defined in the profile."
              },
              {
                "uuid": "df4efb60-c082-4eaa-9c3d-7ea0a77c5195",
                "control-id": "KONF.6.1",
                "description": "This control is implemented as defined in the profile."
              },
              {
                "uuid": "064ea6d1-369c-4e5e-b9c8-12df37dc9ccf",
                "control-id": "KONF.6.1.1",
                "description": "This control is implemented as defined in the profile."
              },
              {
                "uuid": "4f8b6e2d-b3e5-40f2-af69-31bc1aa50c33",
                "control-id": "KONF.6.1.2",
                "description": "This control is implemented as defined in the profile."
              },
              {
                "uuid": "fc047da7-b0cb-4956-b5c5-399c709a6b8c",
                "control-id": "KONF.6.4",
                "description": "This control is implemented as defined in the profile."
              },
              {
                "uuid": "41b17e4d-bd2b-47b2-9262-abd66880df5d",
                "control-id": "KONF.6.4.1",
                "description": "This control is implemented as defined in the profile."
              },
              {
                "uuid": "e65ffee4-cc13-45a7-b2b4-2a2f7131cfbd",
                "control-id": "KONF.6.5",
                "description": "This control is implemented as defined in the profile."
              },
              {
                "uuid": "6a7f7039-b749-4a1b-a0f1-3e9d495d9efe",
                "control-id": "KONF.7.1",
                "description": "This control is implemented as defined in the profile."
              },
              {
                "uuid": "4ea38d28-ab05-4982-b195-47b9079d7bba",
                "control-id": "KONF.7.10",
                "description": "This control is implemented as defined in the profile."
              },
              {
                "uuid": "68297a5f-b046-4707-8b4a-bb1a4373ac77",
                "control-id": "KONF.7.11",
                "description": "This control is implemented as defined in the profile."
              },
              {
                "uuid": "6b2812a9-37cb-4a08-8a96-86e4c8831ed6",
                "control-id": "KONF.7.12",
                "description": "This control is implemented as defined in the profile."
              },
              {
                "uuid": "3e52b1fe-bc7c-4950-8f52-5aa3b60f7bc4",
                "control-id": "KONF.7.13",
                "description": "This control is implemented as defined in the profile."
              },
              {
                "uuid": "9a4ecee7-e7d8-4cda-91cf-a782b6bac517",
                "control-id": "KONF.7.14",
                "description": "This control is implemented as defined in the profile."
              },
              {
                "uuid": "9fc785bc-3b7e-4ae6-8743-fe24950d6afc",
                "control-id": "KONF.7.15",
                "description": "This control is implemented as defined in the profile."
              },
              {
                "uuid": "60509e2f-ba0b-4bc2-ad9d-05c79ce6eb08",
                "control-id": "KONF.7.16",
                "description": "This control is implemented as defined in the profile."
              },
              {
                "uuid": "f46a5608-960c-43d8-836d-b3fd3d76592a",
                "control-id": "KONF.7.16.1",
                "description": "This control is implemented as defined in the profile."
              },
              {
                "uuid": "9112798a-f2df-4aca-a26b-cf3f013c401e",
                "control-id": "KONF.7.2",
                "description": "This control is implemented as defined in the profile."
              },
              {
                "uuid": "fa698535-3cc6-4be7-86df-5cb7717f246d",
                "control-id": "KONF.7.3",
                "description": "This control is implemented as defined in the profile."
              },
              {
                "uuid": "e5994dc0-e7b8-4b43-9167-563944d34e61",
                "control-id": "KONF.7.4",
                "description": "This control is implemented as defined in the profile."
              },
              {
                "uuid": "95df3dfc-27cb-4521-a5f0-0bc4688417f3",
                "control-id": "KONF.7.5",
                "description": "This control is implemented as defined in the profile."
              },
              {
                "uuid": "abea422e-4219-48c7-9fd2-94ba0bc86d79",
                "control-id": "KONF.7.6",
                "description": "This control is implemented as defined in the profile."
              },
              {
                "uuid": "e2ca9a4c-db47-4811-aa85-d3c32edb7d8a",
                "control-id": "KONF.7.7",
                "description": "This control is implemented as defined in the profile."
              },
              {
                "uuid": "2e26db5e-ccf6-49a9-a544-658636c30ba8",
                "control-id": "KONF.7.8",
                "description": "This control is implemented as defined in the profile."
              },
              {
                "uuid": "b2743c0f-270d-45d1-bb16-e6f7670cb640",
                "control-id": "KONF.7.9",
                "description": "This control is implemented as defined in the profile."
              },
              {
                "uuid": "ded4f2a2-82f3-4210-a1f1-bb24481c9826",
                "control-id": "KONF.8.1",
                "description": "This control is implemented as defined in the profile."
              },
              {
                "uuid": "4fa29fcf-49a9-4952-ba12-cf714887a40d",
                "control-id": "KONF.8.1.1",
                "description": "This control is implemented as defined in the profile."
              },
              {
                "uuid": "04c07233-e545-498a-9229-883759d69844",
                "control-id": "KONF.9.1",
                "description": "This control is implemented as defined in the profile."
              },
              {
                "uuid": "49b869ad-7b22-4ce8-9f2e-0a03379f75b0",
                "control-id": "KONF.9.3",
                "description": "This control is implemented as defined in the profile."
              },
              {
                "uuid": "e024e357-4bf9-4b47-ae0c-698e6c427f63",
                "control-id": "NOT.4.2",
                "description": "This control is implemented as defined in the profile."
              }
            ]
          }
        ]
      }
    ]
  }
}